leximpact_common_python_libraries/__init__.py
leximpact_common_python_libraries/_modidx.py
leximpact_common_python_libraries/cache.py
leximpact_common_python_libraries/config.py
leximpact_common_python_libraries/logger.py
leximpact_common_python_libraries-0.1.1.dist-info/LICENSE
leximpact_common_python_libraries-0.1.1.dist-info/METADATA
leximpact_common_python_libraries-0.1.1.dist-info/WHEEL
leximpact_common_python_libraries-0.1.1.dist-info/RECORD
