Metadata-Version: 2.1
Name: leximpact-common-python-libraries
Version: 0.1.1
Summary: Python libraries for LexImpact projects
License: AGPL3
Author: LexImpact
Requires-Python: >=3.9,<4.0
Classifier: License :: Other/Proprietary License
Classifier: Programming Language :: Python :: 3
Classifier: Programming Language :: Python :: 3.9
Classifier: Programming Language :: Python :: 3.10
Classifier: Programming Language :: Python :: 3.11
Provides-Extra: cache
Requires-Dist: nbdev (>=2.3.12,<3.0.0)
Requires-Dist: python-decouple (>=3.5,<4.0)
Requires-Dist: redis (>=3.5.3,<4.0.0) ; extra == "cache"
